visca_over_ip/__init__.py
visca_over_ip/caching_camera.py
visca_over_ip/camera.py
visca_over_ip/exceptions.py
visca_over_ip-0.5.1.dist-info/LICENSE
visca_over_ip-0.5.1.dist-info/METADATA
visca_over_ip-0.5.1.dist-info/WHEEL
visca_over_ip-0.5.1.dist-info/top_level.txt
visca_over_ip-0.5.1.dist-info/RECORD
