Metadata-Version: 2.1
Name: visca_over_ip
Version: 0.5.1
Summary: A driver package for the VISCA over IP protocol used by some Sony PTZ cameras
Home-page: https://github.com/misterhay/VISCA-IP-Controller
Author: Yook74 and misterhay
Author-email: misterhay@gmail.com
License-File: LICENSE
